examples/__init__.py
examples/create_stream.py
examples/data_stream_information.py
examples/enrich_dataframe_with_service.py
examples/get_data.py
examples/get_data_as_files.py
examples/get_dataframe.py
examples/get_delta_data.py
examples/get_delta_dataframe.py
examples/invoke_service.py
examples/replace_stream.py
examples/service_metadata.py
examples/update_stream.py
fusionbase/ACL.py
fusionbase/DataService.py
fusionbase/DataSource.py
fusionbase/DataStream.py
fusionbase/DataStreamCollection.py
fusionbase/Fusionbase.py
fusionbase/__init__.py
fusionbase/constants/ResultType.py
fusionbase/constants/__init__.py
fusionbase/exceptions/DataServiceNotExistsError.py
fusionbase/exceptions/DataStreamNotExistsError.py
fusionbase/exceptions/DataStreamUnsupportedInputError.py
fusionbase/exceptions/DataStreamVersionNotExistsError.py
fusionbase/exceptions/InvalidParameterError.py
fusionbase/exceptions/InvalidRecoverySecretError.py
fusionbase/exceptions/NoDataStreamsFoundError.py
fusionbase/exceptions/NotAuthorizedError.py
fusionbase/exceptions/ResponseEvaluator.py
fusionbase/exceptions/ServerError.py
fusionbase/exceptions/UnauthenticatedError.py
fusionbase/exceptions/UniqueLabelConstraintError.py
fusionbase/exceptions/UnsupportedRollbackError.py
fusionbase/exceptions/__init__.py
fusionbase/utils/DataChunker.py
fusionbase/utils/__init__.py
tests/__init__.py
tests/conftest.py
tests/test_data_service.py
tests/test_data_stream.py
tests/test_data_stream_default_user.py
fusionbase-0.2.9.dist-info/LICENSE
fusionbase-0.2.9.dist-info/METADATA
fusionbase-0.2.9.dist-info/WHEEL
fusionbase-0.2.9.dist-info/top_level.txt
fusionbase-0.2.9.dist-info/RECORD
