Metadata-Version: 2.1
Name: fusionbase
Version: 0.2.9
Summary: This is the main Fusionbase python package to make handling and interacting with data a piece of cake.
Home-page: https://fusionbase.com
Author: Fusionbase
Author-email: info@fusionbase.com
Project-URL: Issues, https://github.com/FusionbaseHQ/fusionbase-python/issues
Project-URL: GitHub, https://github.com/FusionbaseHQ/fusionbase-python
Project-URL: Docs, https://developer.fusionbase.com/docs/developer-sdk/python
Classifier: Programming Language :: Python :: 3
Classifier: License :: OSI Approved :: GNU General Public License v3 (GPLv3)
Classifier: Operating System :: OS Independent
License-File: LICENSE
Requires-Dist: requests-toolbelt
Requires-Dist: tqdm
Requires-Dist: rich
Requires-Dist: pathos
Requires-Dist: aiohttp
Requires-Dist: aiofiles
Requires-Dist: orjson
